docker_volume_dump-0.5.1-py3.8-nspkg.pth
archiver/archive.py
docker_volume_dump-0.5.1.dist-info/METADATA
docker_volume_dump-0.5.1.dist-info/WHEEL
docker_volume_dump-0.5.1.dist-info/entry_points.txt
docker_volume_dump-0.5.1.dist-info/namespace_packages.txt
docker_volume_dump-0.5.1.dist-info/top_level.txt
docker_volume_dump-0.5.1.dist-info/RECORD
