Metadata-Version: 2.1
Name: docker-volume-dump
Version: 0.5.1
Summary: Create your backups based on docker labels
Home-page: https://gitlab.com/micro-entreprise/docker-volume-dump
Author: Pierre Verkest
Author-email: pierreverkest84@gmail.com
License: GPLv3+
Platform: UNKNOWN
Requires-Dist: six
Requires-Dist: docker
